stonfi/__init__.py
stonfi/constants.py
stonfi/utils.py
stonfi/contracts/__init__.py
stonfi/contracts/dex/__init__.py
stonfi/contracts/dex/v1/__init__.py
stonfi/contracts/dex/v1/lp_account.py
stonfi/contracts/dex/v1/pool.py
stonfi/contracts/dex/v1/router.py
stonfi/contracts/farm/__init__.py
stonfi/contracts/jetton/__init__.py
stonfi/contracts/jetton/jetton_root.py
stonfi/contracts/jetton/jetton_wallet.py
stonfi/contracts/pTON/__init__.py
stonfi/contracts/pTON/v1.py
stonfi/http/__init__.py
stonfi/http/api_client.py
stonfi-0.10.dist-info/LICENSE
stonfi-0.10.dist-info/METADATA
stonfi-0.10.dist-info/WHEEL
stonfi-0.10.dist-info/top_level.txt
stonfi-0.10.dist-info/RECORD
